clairesiqi_de_toolkit/__init__.py
clairesiqi_de_toolkit/main.py
clairesiqi_de_toolkit/vm.py
clairesiqi_de_toolkit-0.1.0.dist-info/METADATA
clairesiqi_de_toolkit-0.1.0.dist-info/WHEEL
clairesiqi_de_toolkit-0.1.0.dist-info/entry_points.txt
clairesiqi_de_toolkit-0.1.0.dist-info/RECORD
